common_utils/__init__.py
common_utils/array_utils.py
common_utils/async_utils.py
common_utils/date_utils.py
common_utils/file_utils.py
hj_common_utils-1.2.0.dist-info/METADATA
hj_common_utils-1.2.0.dist-info/WHEEL
hj_common_utils-1.2.0.dist-info/top_level.txt
hj_common_utils-1.2.0.dist-info/RECORD
