Metadata-Version: 2.1
Name: hj-common-utils
Version: 1.2.0
Summary: 各个常用工具类的封装
Author: hj
Author-email: 864655329@qq.com
